__init__.py
tex_generator.py
alexlatexgen-1.0.dist-info/METADATA
alexlatexgen-1.0.dist-info/WHEEL
alexlatexgen-1.0.dist-info/top_level.txt
alexlatexgen-1.0.dist-info/RECORD
