Metadata-Version: 2.1
Name: alexlatexgen
Version: 1.0
Summary: Library for generating tex files
Author: Alexandra Durneva
